camt/__init__.py
camt/__main__.py
camt/camt.py
camt/cli.py
camt/config.py
camt-0.1.3.dist-info/LICENSE
camt-0.1.3.dist-info/METADATA
camt-0.1.3.dist-info/WHEEL
camt-0.1.3.dist-info/entry_points.txt
camt-0.1.3.dist-info/top_level.txt
camt-0.1.3.dist-info/RECORD
