Metadata-Version: 2.1
Name: camt
Version: 0.1.3
Summary: Zip labeled images
Home-page: https://github.com/lucienmakutano/camt
Author: Lucien Makutano
Author-email: makutanolucien@gmail.com
License: MIT
Keywords: camt compression python package
Platform: UNKNOWN
Classifier: Programming Language :: Python :: 3
Classifier: License :: OSI Approved :: MIT License
Classifier: Operating System :: OS Independent
License-File: LICENSE
Requires-Dist: click (==7.1.2)
Requires-Dist: colorama (==0.4.4)
Requires-Dist: pyfastcopy (==1.0.3)
Requires-Dist: shellingham (==1.4.0)
Requires-Dist: typer (==0.3.2)
